instagram/__init__.py
instagram/auth.py
instagram/cache.py
instagram/chat.py
instagram/cli.py
instagram/client.py
instagram/configs.py
instagram/api/__init__.py
instagram/api/analytics.py
instagram/api/direct_messages.py
instagram/api/scheduler.py
instagram/api/utils.py
instagram/chat_ui/__init__.py
instagram/chat_ui/components/__init__.py
instagram/chat_ui/components/chat_window.py
instagram/chat_ui/components/input_box.py
instagram/chat_ui/components/status_bar.py
instagram/chat_ui/interface/__init__.py
instagram/chat_ui/interface/chat_interface.py
instagram/chat_ui/interface/chat_menu.py
instagram/chat_ui/utils/__init__.py
instagram/chat_ui/utils/chat_commands.py
instagram/chat_ui/utils/commands.py
instagram/chat_ui/utils/types.py
instagram/utils/__init__.py
instagram/utils/loading.py
instagram/utils/notification_utils.py
instag_cli-1.4.1.dist-info/METADATA
instag_cli-1.4.1.dist-info/WHEEL
instag_cli-1.4.1.dist-info/entry_points.txt
instag_cli-1.4.1.dist-info/top_level.txt
instag_cli-1.4.1.dist-info/RECORD
