Metadata-Version: 2.4
Name: instag-cli
Version: 1.4.1
Summary: Use Instagram in the terminal, the end of brainrot is here
Author-email: k4ran <k4ran@example.com>
License-Expression: MIT
Project-URL: Homepage, https://github.com/k4ran909/insta-cli
Keywords: instagram,cli,terminal,social-media,tui,command-line,instagram-api
Classifier: Development Status :: 4 - Beta
Classifier: Intended Audience :: End Users/Desktop
Classifier: Natural Language :: English
Classifier: Operating System :: MacOS :: MacOS X
Classifier: Operating System :: POSIX :: Linux
Classifier: Operating System :: OS Independent
Classifier: Programming Language :: Python :: 3.10
Classifier: Programming Language :: Python :: 3.11
Classifier: Programming Language :: Python :: 3.12
Classifier: Programming Language :: Python :: 3 :: Only
Classifier: Environment :: Console
Classifier: Topic :: Utilities
Requires-Python: >=3.10
Requires-Dist: typer==0.20.1
Requires-Dist: art>=6.5
Requires-Dist: pydantic>=2.10.1
Requires-Dist: instagrapi==2.2.1
Requires-Dist: pyyaml>=6.0.2
Requires-Dist: pillow>=11.2.1
Requires-Dist: emoji>=2.14.1
Requires-Dist: requests>=2.32.3
Requires-Dist: click<8.4.0
Requires-Dist: openai>=1.100.1
Requires-Dist: windows-curses; platform_system == "Windows"
